[1,["ad6KFa3MpLPITG9kdqyHW7","bas83z/sFFgKyNyY0gRwNw@f9941","c6urjIpLpFMosnVjfReSHI@f9941","d8yF7dS2FK/bBeHI3/wHwo@f9941","beKncZ/S9JnYdJi3SzTMhz@6c48a","65QEqJXbRPip/RpK0WirZS","90Kmpjw1xILZrgY//UX0dx","4aCyYADHxM3aWbJTgri9m5","6bcgifNChIt7nJOljLxuB8","f0ZcDH7kpOa4I2aoN4SBKE","392rgtMb9Lia1J0eQzDFiL","31kkzLzXlIirFRwQJaSGOV","6d3kO2s+lLIp1nDzlVd3i6","f1BBOqga1Mt4vBMFTauQM9","c7+MrSzS5FArdzLwhnW4H5","b46a+Wi9dAiqehhL4nfS5o@f9941","beKncZ/S9JnYdJi3SzTMhz@f9941","845c85VfpPEosTTONf1GzZ"],["root","node","asset","data","_spriteFrame","_textureSource","_parent","mSpineCtr","_skeletonData"],[["cc.Node",["_name","_layer","_objFlags","__editorExtras__","_prefab","_parent","_components","_children","_lscale"],-1,4,1,9,2,5],["cc.Node",["_name","_layer","_active","_prefab","_children","_parent","_components","_lscale"],0,4,12,1,12,5],"cc.SpriteFrame",["cc.Prefab",["_name"],2],["01fb2AHP7JOdaBB2mcCXkCd",["node","__prefab"],3,1,4],["cc.CompPrefabInfo",["fileId"],2],["cc.PrefabInfo",["fileId","instance","targetOverrides","nestedPrefabInstanceRoots","root","asset"],-1,1,1],["cc.PrefabInfo",["fileId","instance","targetOverrides","root","asset","nestedPrefabInstanceRoots"],0,1,1,2],["cc.PrefabInfo",["fileId","targetOverrides","nestedPrefabInstanceRoots","root","instance","asset"],0,1,4,6],["cc.SpriteRenderer",["node","__prefab","_materials","_spriteFrame"],3,1,4,3,6],["6ad03kHx2dO9JEX0bmEJXhi",["node","__prefab"],3,1,4],["eaa5ax9ilREuqkLZgHN/veM",["node","__prefab"],3,1,4],["cc.TargetInfo",["localID"],2],["cc.PrefabInstance",["fileId","prefabRootNode","propertyOverrides"],2,1,9],["CCPropertyOverrideInfo",["value","propertyPath","targetInfo"],1,1],["CCPropertyOverrideInfo",["propertyPath","targetInfo","value"],2,1,8],["d2ee5IHqxZNS4ECYd8RBboi",["node","__prefab"],3,1,4],["44d66N8v3RBnLeqXjchKHLW",["node","__prefab","mSpineCtr"],3,1,4,1],["cc.UITransform",["node","__prefab"],3,1,4],["cc.RenderRoot2D",["node","__prefab"],3,1,4],["sp.Skeleton",["defaultSkin","defaultAnimation","_premultipliedAlpha","_preCacheMode","loop","node","__prefab"],-2,1,4],["b78cbvS7dBI549xlw5XTqsO",["node","__prefab","mSpine"],3,1,4,1]],[[15,0,1,2,2],[14,0,1,2,3],[5,0,2],[6,0,1,2,3,4,5,5],[0,2,3,5,4,3],[8,0,1,2,3,4,5,4],[12,0,2],[13,0,1,2,2],[3,0,2],[0,0,1,7,6,4,3],[0,0,1,5,6,4,8,3],[9,0,1,2,3,1],[18,0,1,1],[0,0,1,5,4,3],[0,0,1,5,7,6,4,3],[1,0,1,4,3,3],[1,0,2,1,5,6,3,7,4],[4,0,1,1],[7,0,1,2,3,4,5,4],[10,0,1,1],[11,0,1,1],[16,0,1,1],[17,0,1,2,1],[19,0,1,1],[20,0,1,2,3,4,5,6,6],[21,0,1,2,1]],[[[[8,"Reward3"],[9,"Reward3",8388608,[-3],[[17,-2,[2,"6bGZuwjJVPAqQLLrgQIPxG"]]],[3,"20oWDhXSlKQat9+KgIoGCi",null,null,null,-1,0]],[10,"BG",8388608,1,[[11,-4,[2,"7fMjAwvcRKmbFLWywa2Ul2"],[0],1]],[3,"a4kE3I+GNKCqYD9Cx9LiBs",null,null,null,1,0],[1,0.3,0.3,1]]],0,[0,0,1,0,1,1,0,-1,2,0,1,2,0,3,1,4],[0,0],[-1,4],[0,1]],[[[8,"Reward99"],[9,"Reward99",8388608,[-3],[[19,-2,[2,"47hUTBcFFPP6fC7mKa+tCY"]]],[3,"0cGr66njdP4a/bYGGe6LzL",null,null,null,-1,0]],[10,"BG",8388608,1,[[11,-4,[2,"adK/+ynY9Jhqen90Fu2bOg"],[0],1]],[3,"14jRlgCRZEo7dqVEyEgiWH",null,null,null,1,0],[1,0.25,0.25,1]]],0,[0,0,1,0,1,1,0,-1,2,0,1,2,0,3,1,4],[0,0],[-1,4],[0,2]],[[[8,"Reward1"],[9,"Reward1",8388608,[-3],[[20,-2,[2,"6a9lL3PI5I4J1cQdrAGbEN"]]],[3,"a4W3MV/eRPpYgnkHbwpdyx",null,null,null,-1,0]],[10,"BG",8388608,1,[[11,-4,[2,"c9YdvuDR1N65wB8xTEix8E"],[0],1]],[3,"25avehaqBC5ZznxfVw9n8d",null,null,null,1,0],[1,0.35,0.35,1]]],0,[0,0,1,0,1,1,0,-1,2,0,1,2,0,3,1,4],[0,0],[-1,4],[0,3]],[[{"name":"MiddleCoinMap","rect":{"x":0,"y":0,"width":147,"height":96},"offset":{"x":0,"y":0},"originalSize":{"width":147,"height":96},"rotated":false,"capInsets":[0,0,0,0],"vertices":{"rawPosition":[-73.5,-48,0,73.5,-48,0,-73.5,48,0,73.5,48,0],"indexes":[0,1,2,2,1,3],"uv":[0,96,147,96,0,0,147,0],"nuv":[0,0,1,0,0,1,1,1],"minPos":{"x":-73.5,"y":-48,"z":0},"maxPos":{"x":73.5,"y":48,"z":0}},"packable":false,"pixelsToUnit":100,"pivot":{"x":0.5,"y":0.5},"meshType":0}],[2],0,[0],[5],[4]],[[[8,"RewardCtr"],[15,"RewardCtr",8388608,[[[13,"RewardContainer",8388608,-13,[3,"c0lqo+GPZAS6TQnKP+spHw",null,null,null,-12,0]],-14,-15,-16,-17,-18,-19,-20,-21,-22,-23],4,1,1,1,1,1,1,1,1,1,1],[18,"e2AMyZLLpP05WJduYPBtSL",null,null,-11,0,[-1,-2,-3,-4,-5,-6,-7,-8,-9,-10]]],[6,["68+2Ri+VRKuLHBZNrtivk+"]],[6,["a4W3MV/eRPpYgnkHbwpdyx"]],[6,["a4Ivq3s/1G0ZQ2IcDvvBG+"]],[6,["20oWDhXSlKQat9+KgIoGCi"]],[6,["e9cFPbxLxA3IEM/rqT1l9z"]],[6,["30wr993GBNVZ8lPgZ3G62f"]],[6,["67VgqG/ABGvrgyFblRcO/W"]],[6,["0cGr66njdP4a/bYGGe6LzL"]],[6,["b2zn50eJ9Ia6SKNHtPBySE"]],[6,["6dTQsZ9MtA5qkbDLTj9dyu"]],[4,0,{},1,[5,"68+2Ri+VRKuLHBZNrtivk+",null,null,-24,[7,"7boIKuOYtBtZfrTgnJ1Dh9",1,[[1,"Reward0",["_name"],2],[0,["_lpos"],2,[1,0,0,0]],[0,["_lrot"],2,[3,0,0,0,1]],[0,["_euler"],2,[1,0,0,0]],[1,false,["_active"],2]]],0]],[4,0,{},1,[5,"a4W3MV/eRPpYgnkHbwpdyx",null,null,-25,[7,"7cpC5231JMY4Cw1xnU7C6q",1,[[1,"Reward1",["_name"],3],[0,["_lpos"],3,[1,0,0,0]],[0,["_lrot"],3,[3,0,0,0,1]],[0,["_euler"],3,[1,0,0,0]],[1,false,["_active"],3]]],1]],[4,0,{},1,[5,"a4Ivq3s/1G0ZQ2IcDvvBG+",null,null,-26,[7,"afljKmxaVNQ6UyCd+26N+w",1,[[1,"Reward2",["_name"],4],[0,["_lpos"],4,[1,0,0,0]],[0,["_lrot"],4,[3,0,0,0,1]],[0,["_euler"],4,[1,0,0,0]],[1,false,["_active"],4]]],2]],[4,0,{},1,[5,"20oWDhXSlKQat9+KgIoGCi",null,null,-27,[7,"f9gF96TyJEZISFlFIR1bi8",1,[[1,"Reward3",["_name"],5],[0,["_lpos"],5,[1,0,0,0]],[0,["_lrot"],5,[3,0,0,0,1]],[0,["_euler"],5,[1,0,0,0]],[1,false,["_active"],5]]],3]],[4,0,{},1,[5,"e9cFPbxLxA3IEM/rqT1l9z",null,null,-28,[7,"26iWEdKaVBbq+OFbJiQpV+",1,[[1,"Reward4",["_name"],6],[0,["_lpos"],6,[1,0,0,0]],[0,["_lrot"],6,[3,0,0,0,1]],[0,["_euler"],6,[1,0,0,0]],[1,false,["_active"],6]]],4]],[4,0,{},1,[5,"30wr993GBNVZ8lPgZ3G62f",null,null,-29,[7,"6aVFKwKLlHZ5p2dihcUihH",1,[[1,"Reward5",["_name"],7],[0,["_lpos"],7,[1,0,0,0]],[0,["_lrot"],7,[3,0,0,0,1]],[0,["_euler"],7,[1,0,0,0]],[1,false,["_active"],7]]],5]],[4,0,{},1,[5,"67VgqG/ABGvrgyFblRcO/W",null,null,-30,[7,"d6GSKz/uxCFoi3rxGqKHku",1,[[1,"Reward6",["_name"],8],[0,["_lpos"],8,[1,0,0,0]],[0,["_lrot"],8,[3,0,0,0,1]],[0,["_euler"],8,[1,0,0,0]],[1,false,["_active"],8]]],6]],[4,0,{},1,[5,"0cGr66njdP4a/bYGGe6LzL",null,null,-31,[7,"5cCkkGwl9OAaS1ZSC8Ct1f",1,[[1,"Reward99",["_name"],9],[0,["_lpos"],9,[1,0,0,0]],[0,["_lrot"],9,[3,0,0,0,1]],[0,["_euler"],9,[1,0,0,0]],[1,false,["_active"],9]]],7]],[4,0,{},1,[5,"b2zn50eJ9Ia6SKNHtPBySE",null,null,-32,[7,"e8j+DxAZVLIr47+Bwok2xE",1,[[1,"Reward7",["_name"],10],[0,["_lpos"],10,[1,0,0,0]],[0,["_lrot"],10,[3,0,0,0,1]],[0,["_euler"],10,[1,0,0,0]],[1,false,["_active"],10]]],8]],[4,0,{},1,[5,"6dTQsZ9MtA5qkbDLTj9dyu",null,null,-33,[7,"cbIEuflOZA04wWAC7wZDf2",1,[[1,"Reward8",["_name"],11],[0,["_lpos"],11,[1,0,0,0]],[0,["_lrot"],11,[3,0,0,0,1]],[0,["_euler"],11,[1,0,0,0]],[1,false,["_active"],11]]],9]]],0,[0,-1,21,0,-2,20,0,-3,19,0,-4,18,0,-5,17,0,-6,16,0,-7,15,0,-8,14,0,-9,13,0,-10,12,0,0,1,0,0,1,0,6,1,0,-2,12,0,-3,13,0,-4,14,0,-5,15,0,-6,16,0,-7,17,0,-8,18,0,-9,19,0,-10,20,0,-11,21,0,0,12,0,0,13,0,0,14,0,0,15,0,0,16,0,0,17,0,0,18,0,0,19,0,0,20,0,0,21,0,3,1,33],[0,0,0,0,0,0,0,0,0,0],[2,2,2,2,2,2,2,2,2,2],[5,6,7,8,9,10,11,12,13,14]],[[[8,"Reward4"],[9,"Reward4",8388608,[-3],[[21,-2,[2,"02/5kxMQ5FPrGdYT2LcBKI"]]],[3,"e9cFPbxLxA3IEM/rqT1l9z",null,null,null,-1,0]],[10,"BG",8388608,1,[[11,-4,[2,"41YTZdtXdICJTIQWm6qVkC"],[0],1]],[3,"aeGVXTYtNPkqEtcExDtS6N",null,null,null,1,0],[1,0.25,0.25,1]]],0,[0,0,1,0,1,1,0,-1,2,0,1,2,0,3,1,4],[0,0],[-1,4],[0,15]],[[[8,"Reward7"],[9,"Reward7",8388608,[-4,-5],[[22,-3,[2,"92FlPZKhlJKoivvhPe1m51"],-2]],[3,"b2zn50eJ9Ia6SKNHtPBySE",null,null,null,-1,0]],[14,"Node",8388608,1,[-8],[[12,-6,[2,"04ULeWG2RNnZV1Rwbnlb5p"]],[23,-7,[2,"44fTUYzDFPiJaT87UzTq3d"]]],[3,"82q7/cYhZFzaa73kgqxAYh",null,null,null,1,0]],[16,"SpineCtr",false,8388608,2,[[[12,-9,[2,"05CJ4w71xEkJhAQQBQpLxJ"]],-10,-11],4,1,1],[3,"03AB/8HeFIbbaKK4l9ml8t",null,null,null,1,0],[1,0.005,0.005,1]],[10,"BG",8388608,1,[[11,-12,[2,"22HbJNcbZC3o+yGYN0lcxa"],[0],1]],[3,"ef2JjMUP1BWZ2spTjZzwDo",null,null,null,1,0],[1,0.8,0.8,1]],[24,"default","animation",false,0,false,3,[2,"41czDC7HlOk5soiE7Fd+3a"]],[25,3,[2,"70UzHR0DVCqaItYlEA9jB3"],5]],0,[0,0,1,0,7,6,0,1,1,0,-1,4,0,-2,2,0,1,2,0,1,2,0,-1,3,0,1,3,0,-2,5,0,-3,6,0,1,4,0,3,1,12],[0,0,5],[-1,4,8],[0,16,17]]]]
