{"importBase":"import","nativeBase":"native","name":"treasure","deps":["internal","main","resources"],"uuids":["03jCz6MjNKaZNfVnbuh9/v","04be6c571Pi7iDxtTulXBv","04kzIW/S9B7pTZ6ZCssiTv","07p21LXv5HjKr0gSjtZCFc","0dYrGaORtLHIw7n4c8isr0","0da6K8mMFAcIIFb6fbcJHg","0f+uNsdppE9JDyRNsKRhp+","15L6uK8WNBH6XVyZOKl34e","159EMU33ZOaZK7KKSRvOhM","1a4fHGAQ9GRpkfBUYe7mDP","1becZkUrNE6oAVO462+pxr","1dnOsR34FK+6KQi5ZSniiN","1eb4gxKlNJW7hYW6YlM7Eo","20Qd00aT5LVLVcbiOqVkmf","2aA5JQqxxBcojfpCrW8JmD","2bISfI88FIoojQ5Ytt1SeQ","2fN0p87vpMTpzp832UnXRr","31SBoaQPNCO4B+r4uY4GrH","34pIj8M8lLiq5WnlOAwX2V","34vFi9QixKxp9TxAOgQMl/","35BWLzsGlNmZzFyJlAaHqc","3cJePJCJxAybjrbnRrEhnc","3cNcgAXmZNgbvtMZIjphI9","3cVtDOdyNBRY0r15EiTY1b","3dOCCQgldIqowfmsd9WdVO","3dc6FN8TRP+Z4f+/DHl42E","3eAZkTMTZC86EfLkz6bo3w","40poxkuBVI27D5Uwc9nRgY","41fDbmqGxH8KOmkCAcgbI3","44HDb2EaxNUJJvYfTa4cEG","49n7MfPV1G9I7ZNjcFwvqD","49x+GA8W5HG7WTB3klIiuN","4aZzxXKz9HnL2NSC/4oW5l","4bZ75Z3yVFB7MsG0xpl4jM","4cSrmsuy5IK6XSf4TRzZD+","4eqokWeFVOEpz4EjPnD9hB","53CX4nDcBDCp6wKDWL646S","53Juhbj7BLlrkkoHWnZp+Y","57n4lcDEZOyrbpwmSQlBvw","58OJJAA8NOAoB9N1G+Rfi6","5aJxFaThFPApWWzz8xXA3d","61tHNH4SdBD43swMhQBkIt","66T0EgqH5B14eYMy/XdGF0","68TehnFtFOtZyV43u3GE4p","6diqZ0bDBKPocrxQ6i10uc","6eJEEyW2xO1KE3MYwTW/il","70sHkUzxBEeZwFqUpaCx09","71fqHBa2pBMqhA3Xe4Tyrx","715EcrUWFCLaLrWOH4QGZu","76yTT9ibdLIbF7mJZzJJzM","77QyxTIJ9Ix63FXc+PRU9V","7fC+TfxnZDTL1DOcbXogUz","7fGOEMOlJCcL9i6QJI5r11","82BZjVjYBJLbFZDb6AHlKN","83czYhYPlFLonsHkGHB7TB","84N0q1QjxGFpApVF1OGRWb","84SvLx8PpK66kIsAcx8Yed","87vnouBhhCKaOe4alz/+jG","8e2GHlxBZL9reGn4BVAdRc","90XNQdtQJF7K34aAD9yPfg","963BsaYl9NdYG+xuHNMam2","99ksSVXXJOoaIMsxsLVpne","9dH8BPzKxOJbUeGvkh2ehr","9eSJjxlUxLToa1lPOo4bi7","a0n9Ciq4hArJB/N/kO5Xw+","a4YEvBKTZAg63BwMfTEA1K","acJKq2+KhPGq14Q0Hpd74A","b3rq0NOgJODoaiCklrDqO9","b46a+Wi9dAiqehhL4nfS5o","b9kripWFlK1aANImQHOK7K","bas83z/sFFgKyNyY0gRwNw","bcPcYTv2VBmJarDlg8td5U","bcQ9U40F5NVqBOARjc4PSm","bc5ejNv3hLOLYyHMuEuzFG","beKncZ/S9JnYdJi3SzTMhz","c4L82ZP+VE77F+bJaXJqOc","c53w23lHRKirqXqkdJbojW","c6o3h1/thEbZ5NwEtI95gt","c60IixCwdNvLwgtTBY/2lx","c8boioRgZHTYCl/iYvKad5","cbiVKfiGVA47O+iR9+fxFV","d1uiDOzONNRJjPvVKccUT9","d4+OuIlnJDKa6xsiXSmqjs","d6ZV5XoRJMIbw88/kVez5d","d8klJJJRhJ1q2TrqNHOGxx","d8yF7dS2FK/bBeHI3/wHwo","dcNTzLVuxAs5nbYx7HfKzl","e1x0lbf7JCC70YwC990TKB","ed02k1tCtBG6pLdudn+ZfU","effTj1WbFOe7oEUNJCknz9","f29VAudZBBt43wDG+sLtwo","f8hYq03hlBw7BelZGSyyHj","f9JjwZVbxLKYb9Uq4mdk5y","fbskVPotxD9ZwS1BnZEOn2","fdPrxiLIFGV6/ywTY0mghN","00dOwfqdJG45IbBuoaJEdz@f9941","01f2AHSthJwbp6jWeWf1VM","06LcbvOGdFCISp46yFa9sG","06fxeAgAtG7Kreo39xDO9S","06/8Tj4edKiZ4HczqrZu7R","07p21LXv5HjKr0gSjtZCFc@6c48a","07p21LXv5HjKr0gSjtZCFc@f9941","08yDpZn2NKXafVIu7yvrU6","12EEs7AmdHGqXx7Sbto+Jd","15L6uK8WNBH6XVyZOKl34e@6c48a","15L6uK8WNBH6XVyZOKl34e@f9941","171efea4e","17rlsA6ZhHiJ8xAI6lnZOJ","174d+iOfFFNIjvjH2PiVg4","1bbkzdHtBItYsL+6WDf0RL@f9941","1dnOsR34FK+6KQi5ZSniiN@6c48a","1dnOsR34FK+6KQi5ZSniiN@f9941","1ewamOUMJOAI0qP2iNV/om","22PofSqotMmKg2JSny/pUf","26ip7pNk9JVbvBVfmcF0/S","26vLRfyR9M8IaT5Jto7upq@f9941","28QqYs1VZIfJBXL1XRvZRG","28fVcuFntPEpoE1NQVvRay@f9941","29fNm9aW5E+Z9PpHyAWxI3@f9941","293T7dLjlO/Y7onVw7xzO8","2aA5JQqxxBcojfpCrW8JmD@6c48a","2awbME9/hKJ6jGoeT2pgml@f9941","2bISfI88FIoojQ5Ytt1SeQ@6c48a","2cqdHMoBdPHKCWikR+ZFeI","30SqysTnxLD4p9uQcN8xl0@f9941","31SBoaQPNCO4B+r4uY4GrH@6c48a","31SBoaQPNCO4B+r4uY4GrH@f9941","31kkzLzXlIirFRwQJaSGOV","331mWLqU5JOrvTTyaXY8LP","36HpZYtdZAAo0Cv87YNI7S@f9941","392rgtMb9Lia1J0eQzDFiL","3bOogY+6pJZoTG2AvNw4Lz@f9941","3cNcgAXmZNgbvtMZIjphI9@6c48a","3cNcgAXmZNgbvtMZIjphI9@f9941","3cVtDOdyNBRY0r15EiTY1b@6c48a","3cVtDOdyNBRY0r15EiTY1b@f9941","3dOCCQgldIqowfmsd9WdVO@6c48a","3dOCCQgldIqowfmsd9WdVO@f9941","3dc6FN8TRP+Z4f+/DHl42E@6c48a","3dc6FN8TRP+Z4f+/DHl42E@f9941","3e5zSpRAdD8J9ENa6SOH3D","40poxkuBVI27D5Uwc9nRgY@6c48a","40poxkuBVI27D5Uwc9nRgY@f9941","41Xxxau7hN2ruoYhsR3IID@f9941","44HDb2EaxNUJJvYfTa4cEG@6c48a","44HDb2EaxNUJJvYfTa4cEG@f9941","44W0/xh7VG2ojy5gbtvTZo","49iFqmh2tOs6Xzc0wz2M9K","49iahxpp1AOr5LYA1lyJ6N@f9941","49n7MfPV1G9I7ZNjcFwvqD@6c48a","49n7MfPV1G9I7ZNjcFwvqD@f9941","49x+GA8W5HG7WTB3klIiuN@6c48a","4aCyYADHxM3aWbJTgri9m5","4aFnfA9LJCs53Bb06Cr4Qc","4aebZZeUVOR5AzBHzjZljb@f9941","4arbkRvIBKpq9Lc+tC2xc7@f9941","4bZ75Z3yVFB7MsG0xpl4jM@6c48a","4bZ75Z3yVFB7MsG0xpl4jM@f9941","4cSrmsuy5IK6XSf4TRzZD+@6c48a","4cSrmsuy5IK6XSf4TRzZD+@f9941","4eqokWeFVOEpz4EjPnD9hB@6c48a","4eqokWeFVOEpz4EjPnD9hB@f9941","52MD5VNS5GV7zDGodfQhQ6@f9941","53CX4nDcBDCp6wKDWL646S@6c48a","53CX4nDcBDCp6wKDWL646S@f9941","53Juhbj7BLlrkkoHWnZp+Y@6c48a","53Juhbj7BLlrkkoHWnZp+Y@f9941","56cCU8JWpKK5/quBciB7QH@f9941","57n4lcDEZOyrbpwmSQlBvw@6c48a","57n4lcDEZOyrbpwmSQlBvw@f9941","58OJJAA8NOAoB9N1G+Rfi6@6c48a","58OJJAA8NOAoB9N1G+Rfi6@f9941","5aJxFaThFPApWWzz8xXA3d@6c48a","5aJxFaThFPApWWzz8xXA3d@f9941","5cTyDQIcpGwr26Wt5mG2HO@f9941","5coswbA/FLo6ysspsmF8AP","5c2GkSCU1CFpFzIFzczx53","5dhHNH5zJAeLKzKPdodnk8","5enBD85VFAYKfAnXJNHxYO","5fUo/P2LhNO6R4OHRUiUTc@f9941","65QEqJXbRPip/RpK0WirZS","66T0EgqH5B14eYMy/XdGF0@6c48a","66T0EgqH5B14eYMy/XdGF0@f9941","68TehnFtFOtZyV43u3GE4p@6c48a","68TehnFtFOtZyV43u3GE4p@f9941","6aW8HYIaxAsLNZttAxb9/r@f9941","6a0Ebe83lAGLliNGyNuzwy","6bcgifNChIt7nJOljLxuB8","6dhgHBMrZGEryy0p94SyIP","6d3kO2s+lLIp1nDzlVd3i6","6eJEEyW2xO1KE3MYwTW/il@6c48a","6eJEEyW2xO1KE3MYwTW/il@f9941","6fzxm4czVNaISmxT/86d4Y@f9941","70vDfF4bhLeoS4+vaiHRzu","71mKaP85xLuZNNxlCKf2Zn","715EcrUWFCLaLrWOH4QGZu@6c48a","715EcrUWFCLaLrWOH4QGZu@f9941","72TYjVHFNDAJhZDBePQvC4@f9941","73bhRghlNEvqizRAO3cos1@f9941","73j0aR59lKTa3d0sImfAlZ","730dtjeJhLiqjZMtj1WbBM","75UXKlAxJI9Z7zAckRLtmp","76RgVOcdBPbJT7jeiRxl8n@f9941","76yTT9ibdLIbF7mJZzJJzM@6c48a","765bd9FHZL6IKvZdPnJEdB","769PqazS5Ei7yv0cwArEqh@f9941","7c2FyoIZxPi5CUDrps+qen","7eGn2Nw0dKnKbmH8q+v1rT","7fGOEMOlJCcL9i6QJI5r11@6c48a","7fGOEMOlJCcL9i6QJI5r11@f9941","7f8hPhp5JMpZYRqPnOOMf4@f9941","80JdyG3IpLdq/q+zzrZ5ZF@f9941","84N0q1QjxGFpApVF1OGRWb@6c48a","84SvLx8PpK66kIsAcx8Yed@6c48a","84SvLx8PpK66kIsAcx8Yed@f9941","84xZhFfl9FapjGZRXKE/xM@f9941","845c85VfpPEosTTONf1GzZ","85iZiHfW1KDb/f/U2kqsRt","87zHheSydB2rA1XyiDltm6@f9941","878CkcgABALrzzvVdChYdK","8c4GwErYNA4qQ1rChmEE5W@f9941","8epA2PI+pHGKv30HhBMH2s","8fV83hELVDW4G/B/umcCVx@f9941","90Kmpjw1xILZrgY//UX0dx","90UVBoKv5AeZwJphTEQJJU","90XNQdtQJF7K34aAD9yPfg@6c48a","90XNQdtQJF7K34aAD9yPfg@f9941","91/wvE18ZFv5rEbFxyck0K","92BtNqJFZNEbi5I8f+rrYy","99ksSVXXJOoaIMsxsLVpne@6c48a","99ksSVXXJOoaIMsxsLVpne@f9941","9aZo2fw8xM8q20/8Qc8tEH","9a3AJCpu9KE6fvqUK/k9Di","9cg8jYyN1Jl7Fjg5/gHK1L","9eSJjxlUxLToa1lPOo4bi7@6c48a","9eSJjxlUxLToa1lPOo4bi7@f9941","9euepFiElG17c4X42wm5/2","9e9ZjEP7lJJ5tM5HdLl/Cf@f9941","9fVfb3TE9K/ISRILI7zzwp@f9941","a0n9Ciq4hArJB/N/kO5Xw+@6c48a","a0n9Ciq4hArJB/N/kO5Xw+@f9941","a56tuNJJhDR4LDJFCOVckn","a6p751Z39Cc5zJHzVdUThm","ab4SKUaH5PHZjlJilGnocC@f9941","acJKq2+KhPGq14Q0Hpd74A@6c48a","acJKq2+KhPGq14Q0Hpd74A@f9941","ac7od4OelABbZnOh+jyvZJ","afxHkx8GZGsJC+n+YfITQo","b2QfUSA/JFPr+PE+eB+UAC@f9941","b3rq0NOgJODoaiCklrDqO9@6c48a","b3rq0NOgJODoaiCklrDqO9@f9941","b46a+Wi9dAiqehhL4nfS5o@6c48a","b46a+Wi9dAiqehhL4nfS5o@f9941","b5snqx50BDmLQHhI/CssiX","b8XlW9R/hDlqwY4QHKxpFK","b84c1UYyBG3oR4fXRla7/0@f9941","b9UfO4bTpPuZIB/778vdaQ","b9kripWFlK1aANImQHOK7K@6c48a","bah/zejXdHEZ2jJUMLMOUm@f9941","bas83z/sFFgKyNyY0gRwNw@6c48a","bas83z/sFFgKyNyY0gRwNw@f9941","bcPcYTv2VBmJarDlg8td5U@6c48a","bcPcYTv2VBmJarDlg8td5U@f9941","bcQ9U40F5NVqBOARjc4PSm@6c48a","bcQ9U40F5NVqBOARjc4PSm@f9941","bc3dUez6dN9Z0Y9WZ8ij+s@f9941","bc7Cyh5stL159jPaLCxXvx","bdG8q6vX1KcbFDmXyII4Pk","bdh97EwX1Ii6pysAXGsW2Y","beKncZ/S9JnYdJi3SzTMhz@6c48a","beKncZ/S9JnYdJi3SzTMhz@f9941","c0M0FsP8NO3Z1PKWWpd8O/","c1nUl2fH5MSo/ClO5e9UqD@f9941","c1+B17M3hJPora+Ow3pE+n","c3ya/lYypMUKZKtOcUTo52","c4L82ZP+VE77F+bJaXJqOc@6c48a","c4L82ZP+VE77F+bJaXJqOc@f9941","c5sPdxbZ9GW7eeUOjutp4c@f9941","c53w23lHRKirqXqkdJbojW@6c48a","c6o3h1/thEbZ5NwEtI95gt@6c48a","c6o3h1/thEbZ5NwEtI95gt@f9941","c60IixCwdNvLwgtTBY/2lx@6c48a","c7+MrSzS5FArdzLwhnW4H5","c8boioRgZHTYCl/iYvKad5@6c48a","c8boioRgZHTYCl/iYvKad5@f9941","caJ/796P5Bu5NKbZ31emtH","can9AWSk5GdLkgsLb/bTtg@f9941","cbiVKfiGVA47O+iR9+fxFV@6c48a","cb8wSu1i1N6JrsaQxrqBhE@f9941","ccFIx2A3tPF6n2McOHDjQV@f9941","cf/exY9rlEaKiudK/AuXuz@f9941","d1uiDOzONNRJjPvVKccUT9@6c48a","d1uiDOzONNRJjPvVKccUT9@f9941","d1upaDapRDYIFiLzSJgNJl","d2ylN+PwhE3L/erxbQDXXh@f9941","d4+OuIlnJDKa6xsiXSmqjs@6c48a","d4+OuIlnJDKa6xsiXSmqjs@f9941","d6ZV5XoRJMIbw88/kVez5d@6c48a","d6ZV5XoRJMIbw88/kVez5d@f9941","d8dli8pC1Ge7df+wjHG3BD","d8klJJJRhJ1q2TrqNHOGxx@6c48a","d8klJJJRhJ1q2TrqNHOGxx@f9941","d8yF7dS2FK/bBeHI3/wHwo@6c48a","d8yF7dS2FK/bBeHI3/wHwo@f9941","dbBKn6yVdI8quv4Kh+9mDO@f9941","dbyZTWmltAYZ0yMp69twVU@f9941","dcNTzLVuxAs5nbYx7HfKzl@6c48a","dcNTzLVuxAs5nbYx7HfKzl@f9941","ddWZzF3xpEXr2tLNqgRTLl@f9941","dd7ZF7ao1Ksoenjvw6x9xT@f9941","dfmyV+4W9Hipj4PfgXE3Qx@f9941","e1EdXguoJAKLrQpxSeLKUq@f9941","e5TpXmcoBGD5jrrgPZQNne","e72TesY2tD3pGrILY9OI04","e8yY6HLEBKC5Q2ck4zZk3Y@f9941","ecITe6inZOOJc6eGPrF4p9@f9941","effTj1WbFOe7oEUNJCknz9@6c48a","effTj1WbFOe7oEUNJCknz9@f9941","f0ZcDH7kpOa4I2aoN4SBKE","f1BBOqga1Mt4vBMFTauQM9","f6iVrjd8NBybmjxVDNlsHD@f9941","f8hYq03hlBw7BelZGSyyHj@6c48a","f8hYq03hlBw7BelZGSyyHj@f9941","f9oFLIENpFuruSQyq60onD@f9941","f9slGKpzpLsYNqtXCadhtP@f9941","fdIrnmcC5LpJgqMrGtwHMS","fdPrxiLIFGV6/ywTY0mghN@6c48a","fdPrxiLIFGV6/ywTY0mghN@f9941","femdvFRu9H5IzwvyVWjnkp@f9941","ffTBPktl5KD56ktHR+WfQG","ffuIqPr2JI9I8dPLYGRDpD","01a23389e","02cbbc0e0","058402873","05b5f3a22","05de407f0","05e1f27a2","06143ae06","06f0ca178","071efea4e","08af21de0","08e96f815","0908ce09c","0971a4b64","098555c70","09c37df6f","09e302215","0b463ad5e","0bf135f68","0cc62f1be","0cdb339dc","0d085dd84","0d7a80a7b","0d9525dee","0dad19d56","0e57dad65","0ffe982bb","171efea4e@6c48a","20g1ukYUVPvKWKBRznAKo+@f9941","54TknWPwVPqJqeCR+Y/Czo@f9941","57UgcWSMhKGYrPQcn4d3+w@f9941","5857Pn6fpLk6KdilUSkDek","6e8d7+eZdHeps1wYhZ/4Bm","6fAc9/gb9Kfr1dCvwZaWSA@b47c0","7dj5uJT9FMn6OrOOx83tfK@f9941","95EkngnxZFbYuFpsqVTaFr@f9941","ad6KFa3MpLPITG9kdqyHW7","afxHkx8GZGsJC+n+YfITQo@6c48a","afxHkx8GZGsJC+n+YfITQo@f9941","b0BX1MHbRNO5jHDwZIlrrF@f9941","b5snqx50BDmLQHhI/CssiX@6c48a","bdG8q6vX1KcbFDmXyII4Pk@6c48a","bdG8q6vX1KcbFDmXyII4Pk@f9941","d0MqyYBeFAkIi762QNy1/B@b47c0","d1NGQ2rJZCcbhjH0/erZWw","e6ydMP4UpBiZd+EuiSCZ7l","ffuIqPr2JI9I8dPLYGRDpD@6c48a","ffuIqPr2JI9I8dPLYGRDpD@f9941"],"paths":{"0":["music/HintClick",5,1],"1":["music/CoinExplode",5,1],"2":["spine/baojinbi",6,1],"3":["bg/FrameBG",3,1],"4":["music/Lose",5,1],"5":["Default",1,1],"6":["music/Loop0",5,1],"7":["atlas/map/SmallCoin3",3,1],"8":["spine/shengliyanhua",6,1],"9":["music/Dice",5,1],"10":["music/Win",5,1],"11":["atlas/treasure/20",3,1],"12":["music/StartDig",5,1],"13":["music/FireWork1",5,1],"14":["spine/yanhua",3,1],"15":["spine/baobi_418",3,1],"16":["spine/000031_jinbixialuo",6,1],"17":["bg/Guide",3,1],"18":["music/ManyCoins",5,1],"19":["music/RewardShow",5,1],"20":["spine/yanhua",6,1],"21":["music/Dig",5,1],"22":["atlas/treasure/5",3,1],"23":["bg/map0",3,1],"24":["atlas/treasure/10",3,1],"25":["atlas/map/Shovel",3,1],"26":["music/GiftShow0",5,1],"27":["bg/Fake",3,1],"28":["music/Bomb",5,1],"29":["atlas/treasure/18",3,1],"30":["bg/DQ0",3,1],"31":["spine/caidai",3,1],"32":["spine/E8",6,1],"33":["atlas/treasure/4",3,1],"34":["atlas/treasure/21",3,1],"35":["bg/TreasureBG",3,1],"36":["atlas/treasure/15",3,1],"37":["atlas/treasure/14",3,1],"38":["bg/HallBG",3,1],"39":["atlas/map/Frame2",3,1],"40":["atlas/map/Frame3",3,1],"41":["spine/3D_sonli",6,1],"42":["atlas/treasure/0",3,1],"43":["atlas/treasure/7",3,1],"44":["music/DoubleLife",5,1],"45":["atlas/treasure/3",3,1],"46":["music/DealPoker",5,1],"47":["music/GetBag",5,1],"48":["atlas/treasure/22",3,1],"49":["spine/3D_sonli",3,1],"50":["music/Rotate",5,1],"51":["music/BGM0",5,1],"52":["atlas/treasure/23",3,1],"53":["music/ManyCoins2",5,1],"54":["music/Cele",5,1],"55":["spine/E8",3,1],"56":["atlas/map/Frame4",3,1],"57":["music/BigWin2",5,1],"58":["music/SmallCoin",5,1],"59":["atlas/treasure/19",3,1],"60":["music/NumberRaise",5,1],"61":["atlas/treasure/16",3,1],"62":["music/RewardWindow",5,1],"63":["atlas/treasure/6",3,1],"64":["atlas/treasure/9",3,1],"65":["music/BGM1",5,1],"66":["atlas/map/Frame1",3,1],"67":["atlas/map/SuperCoinMap",3,1],"68":["atlas/reward/2",3,1],"69":["spine/000031_jinbixialuo",3,1],"70":["atlas/reward/1",3,1],"71":["atlas/treasure/17",3,1],"72":["atlas/treasure/12",3,1],"73":["music/BigWin1",5,1],"74":["atlas/map/MiddleCoinMap",3,1],"75":["atlas/reward/3",3,1],"76":["spine/shengliyanhua",3,1],"77":["atlas/treasure/13",3,1],"78":["par/res/Explosion",3,1],"79":["atlas/treasure/1",3,1],"80":["spine/baojinbi",3,1],"81":["bg/DQ1",3,1],"82":["atlas/treasure/2",3,1],"83":["bg/DQ2",3,1],"84":["atlas/reward/4",3,1],"85":["atlas/reward/0",3,1],"86":["atlas/treasure/8",3,1],"87":["music/Cele2",5,1],"88":["music/GiftShow1",5,1],"89":["atlas/treasure/11",3,1],"90":["music/BigCoin",5,1],"91":["atlas/map/Frame0",3,1],"92":["spine/caidai",6,1],"93":["spine/baobi_418",6,1],"94":["atlas/map/BigCoinMap",3,1],"95":["atlas/MoneyBar/spriteFrame",2,1],"96":["prefabs/map/MapCtr",0,1],"97":["par/res/Explosion",8,1],"98":["prefabs/ui/TreasureItem",0,1],"99":["prefabs/ui/MapUI",0,1],"100":["bg/FrameBG/texture",4,1],"101":["bg/FrameBG/spriteFrame",2,1],"102":["prefabs/ui/WinUI",0,1],"103":["spine/000031_jinbixialuo",7,1],"104":["atlas/map/SmallCoin3/texture",4,1],"105":["atlas/map/SmallCoin3/spriteFrame",2,1],"107":["prefabs/ui/rewardCreate/RewardCreateUI1",0,1],"108":["prefabs/ui/rewardCreate/RewardCreateUI3",0,1],"109":["atlas/Confirm/spriteFrame",2,1],"110":["atlas/treasure/20/texture",4,1],"111":["atlas/treasure/20/spriteFrame",2,1],"112":["prefabs/ui/GuideWindow",0,1],"113":["prefabs/ui/PaiMaiUI",0,1],"114":["prefabs/shovel/Shovel",0,1],"115":["atlas/ChargeTitle/spriteFrame",2,1],"116":["prefabs/ui/rewardCreate/RewardCreateUI0",0,1],"117":["atlas/SuperCoin/spriteFrame",2,1],"118":["atlas/Bar0/spriteFrame",2,1],"119":["spine/baojinbi",7,1],"120":["spine/yanhua/texture",4,1],"121":["atlas/Clound1/spriteFrame",2,1],"122":["spine/baobi_418/texture",4,1],"123":["prefabs/item/Item2",0,1],"124":["atlas/DangerTag/spriteFrame",2,1],"125":["bg/Guide/texture",4,1],"126":["bg/Guide/spriteFrame",2,1],"127":["prefabs/reward/Reward6",0,1],"128":["prefabs/ui/BuyUI",0,1],"129":["atlas/RuleBtn/spriteFrame",2,1],"130":["prefabs/reward/Reward5",0,1],"131":["atlas/Confirm2/spriteFrame",2,1],"132":["atlas/treasure/5/texture",4,1],"133":["atlas/treasure/5/spriteFrame",2,1],"134":["bg/map0/texture",4,1],"135":["bg/map0/spriteFrame",2,1],"136":["atlas/treasure/10/texture",4,1],"137":["atlas/treasure/10/spriteFrame",2,1],"138":["atlas/map/Shovel/texture",4,1],"139":["atlas/map/Shovel/spriteFrame",2,1],"140":["prefabs/ui/DoubleLifeUI",0,1],"141":["bg/Fake/texture",4,1],"142":["bg/Fake/spriteFrame",2,1],"143":["atlas/LoseUI/spriteFrame",2,1],"144":["atlas/treasure/18/texture",4,1],"145":["atlas/treasure/18/spriteFrame",2,1],"146":["prefabs/ui/rewardCreate/RewardCreateUI",0,1],"147":["prefabs/ui/WinCoinUI",0,1],"148":["atlas/Btn100/spriteFrame",2,1],"149":["bg/DQ0/texture",4,1],"150":["bg/DQ0/spriteFrame",2,1],"151":["spine/caidai/texture",4,1],"152":["prefabs/reward/Reward2",0,1],"153":["prefabs/item/Item3",0,1],"154":["atlas/Btn1000/spriteFrame",2,1],"155":["atlas/CoinReward/spriteFrame",2,1],"156":["atlas/treasure/4/texture",4,1],"157":["atlas/treasure/4/spriteFrame",2,1],"158":["atlas/treasure/21/texture",4,1],"159":["atlas/treasure/21/spriteFrame",2,1],"160":["bg/TreasureBG/texture",4,1],"161":["bg/TreasureBG/spriteFrame",2,1],"162":["atlas/DoubleLifeIcon/spriteFrame",2,1],"163":["atlas/treasure/15/texture",4,1],"164":["atlas/treasure/15/spriteFrame",2,1],"165":["atlas/treasure/14/texture",4,1],"166":["atlas/treasure/14/spriteFrame",2,1],"167":["atlas/SmallCoin2/spriteFrame",2,1],"168":["bg/HallBG/texture",4,1],"169":["bg/HallBG/spriteFrame",2,1],"170":["atlas/map/Frame2/texture",4,1],"171":["atlas/map/Frame2/spriteFrame",2,1],"172":["atlas/map/Frame3/texture",4,1],"173":["atlas/map/Frame3/spriteFrame",2,1],"174":["atlas/Frame/spriteFrame",2,1],"175":["prefabs/ui/rewardCreate/RewardCreateUI4",0,1],"176":["prefabs/map/HexCell",0,1],"177":["spine/yanhua",7,1],"178":["spine/3D_sonli",7,1],"179":["atlas/Dice4/spriteFrame",2,1],"180":["prefabs/reward/Reward0",0,1],"181":["atlas/treasure/0/texture",4,1],"182":["atlas/treasure/0/spriteFrame",2,1],"183":["atlas/treasure/7/texture",4,1],"184":["atlas/treasure/7/spriteFrame",2,1],"185":["atlas/DrawTitle/spriteFrame",2,1],"186":["par/res/SmallExplosion",0,1],"187":["prefabs/reward/Reward3",0,1],"188":["prefabs/ui/ItemCtrUI",0,1],"189":["prefabs/reward/Reward99",0,1],"190":["atlas/treasure/3/texture",4,1],"191":["atlas/treasure/3/spriteFrame",2,1],"192":["atlas/SettingBtn/spriteFrame",2,1],"193":["prefabs/shovel/ShovelCtr",0,1],"194":["spine/shengliyanhua",7,1],"195":["atlas/treasure/22/texture",4,1],"196":["atlas/treasure/22/spriteFrame",2,1],"197":["atlas/ItemCtr/spriteFrame",2,1],"198":["atlas/TreasureItemBG/spriteFrame",2,1],"199":["prefabs/ui/rewardCreate/MiniGame2",0,1],"200":["prefabs/ui/rewardCreate/CombineCard",0,1],"201":["prefabs/ui/rewardCreate/RewardCreateUI2",0,1],"202":["atlas/TreasureTitle/spriteFrame",2,1],"203":["spine/3D_sonli/texture",4,1],"204":["prefabs/ui/MoneyUI",0,1],"205":["atlas/GetRewardBtn/spriteFrame",2,1],"206":["prefabs/ui/rewardCreate/Card",0,1],"207":["prefabs/item/Item4",0,1],"208":["atlas/treasure/23/texture",4,1],"209":["atlas/treasure/23/spriteFrame",2,1],"210":["atlas/Dice1/spriteFrame",2,1],"211":["atlas/DrawBtn/spriteFrame",2,1],"212":["spine/E8/texture",4,1],"213":["atlas/map/Frame4/texture",4,1],"214":["atlas/map/Frame4/spriteFrame",2,1],"215":["atlas/WinTitle/spriteFrame",2,1],"216":["spine/E8",7,1],"217":["prefabs/ui/UseItemUI",0,1],"218":["atlas/SubBG/spriteFrame",2,1],"219":["prefabs/item/Item1",0,1],"220":["atlas/Dice0/spriteFrame",2,1],"221":["spine/baobi_418",7,1],"222":["atlas/Clound0/spriteFrame",2,1],"223":["prefabs/reward/Reward1",0,1],"224":["prefabs/ui/LoseUI",0,1],"225":["atlas/treasure/19/texture",4,1],"226":["atlas/treasure/19/spriteFrame",2,1],"227":["prefabs/ui/DangerTipsUI",0,1],"228":["prefabs/ui/WelcomeUI",0,1],"229":["atlas/treasure/16/texture",4,1],"230":["atlas/treasure/16/spriteFrame",2,1],"231":["prefabs/ui/GiftUI",0,1],"232":["prefabs/ui/ShopUI",0,1],"233":["prefabs/item/Item0",0,1],"234":["atlas/treasure/6/texture",4,1],"235":["atlas/treasure/6/spriteFrame",2,1],"236":["prefabs/ui/TreasureAnmUI",0,1],"237":["atlas/Bomb/spriteFrame",2,1],"238":["atlas/BtnDrawNow/spriteFrame",2,1],"239":["atlas/treasure/9/texture",4,1],"240":["atlas/treasure/9/spriteFrame",2,1],"241":["par/res/Embers",8,1],"242":["prefabs/ui/rewardCreate/MiniGame4",0,1],"243":["atlas/TapStart/spriteFrame",2,1],"244":["atlas/map/Frame1/texture",4,1],"245":["atlas/map/Frame1/spriteFrame",2,1],"246":["prefabs/ui/TipsUI",0,1],"248":["atlas/Input/spriteFrame",2,1],"249":["atlas/map/SuperCoinMap/texture",4,1],"250":["atlas/map/SuperCoinMap/spriteFrame",2,1],"251":["atlas/reward/2/texture",4,1],"252":["atlas/reward/2/spriteFrame",2,1],"254":["prefabs/ui/TreasureComboItem",0,1],"255":["atlas/CardB/spriteFrame",2,1],"256":["prefabs/ui/DrawUI",0,1],"257":["spine/000031_jinbixialuo/texture",4,1],"258":["atlas/Buy/spriteFrame",2,1],"259":["atlas/reward/1/texture",4,1],"260":["atlas/reward/1/spriteFrame",2,1],"261":["atlas/treasure/17/texture",4,1],"262":["atlas/treasure/17/spriteFrame",2,1],"263":["atlas/treasure/12/texture",4,1],"264":["atlas/treasure/12/spriteFrame",2,1],"265":["atlas/Question/spriteFrame",2,1],"266":["prefabs/ui/rewardCreate/MiniGame0",0,1],"268":["prefabs/ui/Toast",0,1],"269":["atlas/map/MiddleCoinMap/texture",4,1],"270":["atlas/map/MiddleCoinMap/spriteFrame",2,1],"271":["prefabs/ui/HallUI",0,1],"272":["atlas/BtnChargeNow/spriteFrame",2,1],"273":["prefabs/ui/TipsButtonUI",0,1],"274":["prefabs/ui/MenuUI",0,1],"275":["atlas/reward/3/texture",4,1],"276":["atlas/reward/3/spriteFrame",2,1],"277":["atlas/Dice2/spriteFrame",2,1],"278":["spine/shengliyanhua/texture",4,1],"279":["atlas/treasure/13/texture",4,1],"280":["atlas/treasure/13/spriteFrame",2,1],"281":["par/res/Explosion/texture",4,1],"282":["prefabs/reward/Reward8",0,1],"283":["atlas/treasure/1/texture",4,1],"284":["atlas/treasure/1/spriteFrame",2,1],"285":["prefabs/ui/BigWinUI",0,1],"286":["atlas/DangerProgress/spriteFrame",2,1],"287":["spine/baojinbi/texture",4,1],"288":["atlas/Gear/spriteFrame",2,1],"289":["atlas/QuitBtn/spriteFrame",2,1],"290":["atlas/Back/spriteFrame",2,1],"291":["bg/DQ1/texture",4,1],"292":["bg/DQ1/spriteFrame",2,1],"293":["prefabs/reward/RewardCtr",0,1],"294":["atlas/StartBtn/spriteFrame",2,1],"295":["atlas/treasure/2/texture",4,1],"296":["atlas/treasure/2/spriteFrame",2,1],"297":["bg/DQ2/texture",4,1],"298":["bg/DQ2/spriteFrame",2,1],"299":["spine/caidai",7,1],"300":["atlas/reward/4/texture",4,1],"301":["atlas/reward/4/spriteFrame",2,1],"302":["atlas/reward/0/texture",4,1],"303":["atlas/reward/0/spriteFrame",2,1],"304":["atlas/SmallCoin4/spriteFrame",2,1],"305":["atlas/QuitGame/spriteFrame",2,1],"306":["atlas/treasure/8/texture",4,1],"307":["atlas/treasure/8/spriteFrame",2,1],"308":["atlas/CardF/spriteFrame",2,1],"309":["atlas/ChargeBtn/spriteFrame",2,1],"310":["atlas/Cancel/spriteFrame",2,1],"311":["atlas/Dice5/spriteFrame",2,1],"312":["prefabs/ui/IntroUI",0,1],"313":["prefabs/ui/mapProgress/MapProgress",0,1],"314":["atlas/MenuBG/spriteFrame",2,1],"315":["atlas/CoinBG/spriteFrame",2,1],"316":["atlas/treasure/11/texture",4,1],"317":["atlas/treasure/11/spriteFrame",2,1],"318":["prefabs/reward/Reward4",0,1],"319":["prefabs/reward/Reward7",0,1],"320":["atlas/Btn200/spriteFrame",2,1],"321":["atlas/map/Frame0/texture",4,1],"322":["atlas/map/Frame0/spriteFrame",2,1],"323":["atlas/PaiMaiBtn/spriteFrame",2,1],"324":["atlas/Dice3/spriteFrame",2,1],"325":["prefabs/ui/rewardCreate/MiniGame1",0,1],"326":["atlas/map/BigCoinMap/texture",4,1],"327":["atlas/map/BigCoinMap/spriteFrame",2,1],"328":["atlas/BigCoin/spriteFrame",2,1],"329":["prefabs/ui/CloudUI",0,1]},"scenes":{"db://assets/treasure/Default.scene":5},"packs":{"01a23389e":[123,252],"02cbbc0e0":[113,142],"058402873":[114,139],"05b5f3a22":[169,232],"05de407f0":[282,327],"05e1f27a2":[108,260],"06143ae06":[103,147,194],"06f0ca178":[119,221,285],"071efea4e":[95,109,115,117,118,121,124,129,131,143,148,154,155,162,167,174,179,185,192,197,198,202,205,210,211,215,218,220,222,237,238,243,248,255,258,265,272,277,286,288,289,290,294,304,305,308,309,310,311,314,315,320,323,324,328],"08af21de0":[130,301],"08e96f815":[102,161,177,182,299],"0908ce09c":[5,329],"0971a4b64":[101,128,372],"098555c70":[127,250],"09c37df6f":[110,120,122,132,134,138,136,156,158,160,172,190,100,208,234,141,151,195,203,104,357,144,149,168,181,183,213,225,165,229,125,163,212,170,239,244,367,249,251,370,257,259,261,263,371,269,278,279,281,275,283,287,291,295,302,297,300,306,316,321,326,376],"09e302215":[153,188,207,219,233],"0b463ad5e":[96,97,135,150,171,173,176,186,362,214,241,245,366,292,298,322],"0bf135f68":[107,303],"0cc62f1be":[178,231,296],"0cdb339dc":[98,284],"0d085dd84":[112,126],"0d7a80a7b":[200,242,368,377],"0d9525dee":[187,189,223,270,293,318,319],"0dad19d56":[199,206],"0e57dad65":[105,180,216],"0ffe982bb":[152,276]},"versions":{"import":[331,"44e9a",332,"e1057",0,"c1ab8",1,"aec1b",2,"88362",333,"fce09",334,"9dbd7",335,"7a12c",336,"45cd4",337,"f21e6",338,"89577",99,"680f8",339,"f7cc4",3,"a2533",340,"6a87c",341,"f9019",342,"fafc5",343,"84bdf",344,"bdf7f",345,"60ab1",346,"e97ce",347,"843b9",348,"12b66",349,"fd4a2",350,"c86d3",351,"e443d",4,"dd25d",352,"839ab",353,"95247",354,"11dcd",355,"0008e",6,"237ed",356,"53312",7,"a2533",8,"e4ff7",106,"5a4c6",9,"221f6",10,"2e90e",11,"a2533",111,"8ce74",12,"b2373",13,"2ec5c",116,"538af",14,"a2533",15,"a2533",16,"97e57",17,"a2533",18,"4dfda",19,"59149",20,"a3b5c",21,"3706d",22,"a2533",133,"86401",23,"c16a8",24,"a2533",137,"07f22",25,"a2533",26,"e7da8",140,"52871",27,"c16a8",28,"8fad4",29,"a2533",145,"d513a",146,"b2456",30,"a2533",31,"a2533",32,"c6c8b",33,"a2533",157,"52d3c",34,"a2533",159,"d4972",35,"a2533",36,"a2533",164,"5aed5",37,"a2533",166,"6dc61",38,"c16a8",39,"a2533",40,"a2533",175,"d8c28",41,"c1d37",42,"a2533",43,"a2533",184,"c0f48",44,"abec8",45,"a2533",191,"1b0a4",46,"626fc",193,"9454a",47,"80a22",48,"a2533",196,"32f23",201,"28fc6",49,"a2533",204,"cc1f4",50,"63742",51,"1d0ee",52,"a2533",209,"bf882",53,"d3b21",54,"c8129",55,"a2533",56,"a2533",217,"c82ff",57,"56944",58,"3e345",224,"63c50",59,"a2533",226,"4c651",227,"abf6d",228,"37eb1",60,"db530",61,"a2533",230,"67a26",62,"60360",63,"a2533",235,"5dc7c",236,"97962",64,"a2533",240,"1bb00",65,"1cf9b",66,"a2533",246,"39c25",247,"a2533",67,"a2533",68,"a2533",253,"a2533",254,"56da4",256,"ac39b",69,"a2533",70,"a2533",71,"a2533",262,"8471d",72,"a2533",264,"6d729",73,"cf5b9",266,"ee44b",267,"a2533",268,"31036",74,"a2533",271,"6385a",273,"7ec28",274,"133b2",75,"a2533",76,"a2533",77,"a2533",280,"6ccec",78,"a2533",79,"a2533",80,"a2533",81,"a2533",82,"a2533",83,"a2533",84,"a2533",85,"a2533",86,"a2533",307,"f8fd3",87,"f1993",312,"d7de5",313,"a6539",88,"c7109",89,"a2533",317,"c6851",90,"453b3",91,"a2533",92,"bf044",93,"b2506",325,"e5c45",94,"a2533",330,"a2533"],"native":[0,"9660d",1,"b0501",2,"081da",3,"d5222",4,"19796",6,"ed55e",7,"cd3fa",8,"d4352",106,"97f15",9,"34f1a",10,"74196",11,"b8ac4",12,"a75bb",13,"5ead8",14,"70804",15,"449e2",16,"d7f5b",17,"73901",18,"6f048",19,"16c35",20,"d264e",21,"3decd",22,"1158c",23,"95d59",24,"6cee5",25,"5f507",26,"43b2e",27,"0bdc5",28,"0f59a",29,"1fa25",30,"d0b85",31,"76e28",32,"a612c",33,"66415",34,"a43d6",35,"b0cbc",36,"9d6d9",37,"c97c2",38,"556b6",39,"dc392",40,"fd136",41,"5375d",42,"7f2e8",43,"fea5d",44,"42b49",45,"3182c",46,"dfc28",47,"4b6ee",48,"710a8",49,"b1214",50,"d92b5",51,"319ae",52,"d40cb",53,"eb216",54,"a360a",55,"5a33c",56,"69172",57,"01de3",58,"0de8c",59,"843ac",60,"11761",61,"f354e",62,"b84e9",63,"5b4fe",64,"30242",65,"de32c",66,"ed7f3",247,"d55c2",67,"dda9d",68,"6eeb9",253,"5d63c",69,"9ca06",70,"f408f",71,"6da9a",72,"d2112",73,"f6209",267,"17df6",74,"896ba",75,"28266",76,"245ce",77,"ed733",78,"ec644",79,"7d8fc",80,"2bddd",81,"6df18",82,"341b3",83,"8e080",84,"58845",85,"26a29",86,"894dc",87,"c8d37",88,"162ac",89,"b76b3",90,"17c4d",91,"8f49a",92,"39d84",93,"0404c",94,"9c5b9",330,"6d707"]},"redirect":[358,"2",359,"2",360,"2",361,"2",363,"1",364,"2",365,"2",369,"1",373,"1",374,"0",375,"2"],"debug":false,"extensionMap":{},"hasPreloadScript":true,"dependencyRelationships":{},"types":["cc.Prefab","cc.SceneAsset","cc.SpriteFrame","cc.ImageAsset","cc.Texture2D","cc.AudioClip","cc.Asset","sp.SkeletonData","cc.Material"]}